ipex_llm/__init__.py
ipex_llm/convert_model.py
ipex_llm/llm_patching.py
ipex_llm/models.py
ipex_llm/optimize.py
ipex_llm/setup.py
ipex_llm/__pycache__/__init__.cpython-311.pyc
ipex_llm/__pycache__/convert_model.cpython-311.pyc
ipex_llm/__pycache__/llm_patching.cpython-311.pyc
ipex_llm/__pycache__/models.cpython-311.pyc
ipex_llm/__pycache__/optimize.cpython-311.pyc
ipex_llm/__pycache__/setup.cpython-311.pyc
ipex_llm/cli/llm-chat
ipex_llm/cli/llm-chat.ps1
ipex_llm/cli/llm-cli
ipex_llm/cli/llm-cli.ps1
ipex_llm/cli/prompts/chat-with-llm.txt
ipex_llm/ggml/__init__.py
ipex_llm/ggml/convert.py
ipex_llm/ggml/convert_model.py
ipex_llm/ggml/quantize.py
ipex_llm/ggml/__pycache__/__init__.cpython-311.pyc
ipex_llm/ggml/__pycache__/convert.cpython-311.pyc
ipex_llm/ggml/__pycache__/convert_model.cpython-311.pyc
ipex_llm/ggml/__pycache__/quantize.cpython-311.pyc
ipex_llm/ggml/model/__init__.py
ipex_llm/ggml/model/__pycache__/__init__.cpython-311.pyc
ipex_llm/ggml/model/bloom/__init__.py
ipex_llm/ggml/model/bloom/bloom.py
ipex_llm/ggml/model/bloom/bloom_cpp.py
ipex_llm/ggml/model/bloom/__pycache__/__init__.cpython-311.pyc
ipex_llm/ggml/model/bloom/__pycache__/bloom.cpython-311.pyc
ipex_llm/ggml/model/bloom/__pycache__/bloom_cpp.cpython-311.pyc
ipex_llm/ggml/model/generation/__init__.py
ipex_llm/ggml/model/generation/utils.py
ipex_llm/ggml/model/generation/__pycache__/__init__.cpython-311.pyc
ipex_llm/ggml/model/generation/__pycache__/utils.cpython-311.pyc
ipex_llm/ggml/model/gptneox/__init__.py
ipex_llm/ggml/model/gptneox/gptneox.py
ipex_llm/ggml/model/gptneox/gptneox_cpp.py
ipex_llm/ggml/model/gptneox/gptneox_types.py
ipex_llm/ggml/model/gptneox/__pycache__/__init__.cpython-311.pyc
ipex_llm/ggml/model/gptneox/__pycache__/gptneox.cpython-311.pyc
ipex_llm/ggml/model/gptneox/__pycache__/gptneox_cpp.cpython-311.pyc
ipex_llm/ggml/model/gptneox/__pycache__/gptneox_types.cpython-311.pyc
ipex_llm/ggml/model/llama/__init__.py
ipex_llm/ggml/model/llama/llama.py
ipex_llm_fix-2.1.2.dist-info/METADATA
ipex_llm_fix-2.1.2.dist-info/WHEEL
ipex_llm_fix-2.1.2.dist-info/top_level.txt
ipex_llm_fix-2.1.2.dist-info/RECORD
